molcomplex/__init__.py
molcomplex/__main__.py
molcomplex/complex_funcs.py
molcomplex/complex_object.py
molcomplex/descriptors.py
molcomplex/molcomplex.py
molcomplex/metrics/bertz.f
molcomplex/metrics/boettcher.py
molcomplex/metrics/fpscores.pkl.gz
molcomplex/metrics/proudfoot.py
molcomplex/metrics/rucker_twc.py
molcomplex/metrics/sa_score.py
molcomplex/metrics/sps_score.py
molcomplex/metrics/standalone_model_numpy.py
molcomplex/models/example_model/checkpoint
molcomplex/models/example_model/model.ckpt-1.meta
molcomplex/models/example_model/model.ckpt-10.meta
molcomplex/models/example_model/model.ckpt-11.meta
molcomplex/models/example_model/model.ckpt-12.meta
molcomplex/models/example_model/model.ckpt-13.meta
molcomplex/models/example_model/model.ckpt-14.meta
molcomplex/models/example_model/model.ckpt-15.meta
molcomplex/models/example_model/model.ckpt-16.meta
molcomplex/models/example_model/model.ckpt-17.meta
molcomplex/models/example_model/model.ckpt-18.meta
molcomplex/models/example_model/model.ckpt-19.meta
molcomplex/models/example_model/model.ckpt-2.meta
molcomplex/models/example_model/model.ckpt-20.meta
molcomplex/models/example_model/model.ckpt-21.meta
molcomplex/models/example_model/model.ckpt-22.meta
molcomplex/models/example_model/model.ckpt-23.meta
molcomplex/models/example_model/model.ckpt-24.meta
molcomplex/models/example_model/model.ckpt-25.meta
molcomplex/models/example_model/model.ckpt-26.meta
molcomplex/models/example_model/model.ckpt-27.meta
molcomplex/models/example_model/model.ckpt-28.meta
molcomplex/models/example_model/model.ckpt-29.meta
molcomplex/models/example_model/model.ckpt-3.meta
molcomplex/models/example_model/model.ckpt-30.meta
molcomplex/models/example_model/model.ckpt-31.meta
molcomplex/models/example_model/model.ckpt-32.meta
molcomplex/models/example_model/model.ckpt-33.meta
molcomplex/models/example_model/model.ckpt-34.meta
molcomplex/models/example_model/model.ckpt-35.meta
molcomplex/models/example_model/model.ckpt-36.meta
molcomplex-1.0.3.dist-info/LICENSE
molcomplex-1.0.3.dist-info/METADATA
molcomplex-1.0.3.dist-info/WHEEL
molcomplex-1.0.3.dist-info/top_level.txt
molcomplex-1.0.3.dist-info/RECORD
