Metadata-Version: 2.1
Name: molcomplex
Version: 1.0.3
Summary: Molecular Complexity Calculations
Home-page: https://github.com/patonlab/molcomplex
Download-URL: https://github.com/patonlab/molcomplex/archive/refs/tags/v1.0.3.tar.gz
Author: Guilian Luchini, Shree Sowndarya S. V.
Author-email: guilian.luchini@colostate.edu, svss@colostate.edu
License: MIT
Keywords: workflows,computational chemistry,cheminformatics,molecular complexity,DFT,automation
Requires-Python: >=3.0
License-File: LICENSE
Requires-Dist: brotli ==1.1.0
Requires-Dist: click ==8.1.3
Requires-Dist: dash-bootstrap-components ==1.6.0
Requires-Dist: dash-core-components ==2.0.0
Requires-Dist: dash-dangerously-set-inner-html ==0.0.2
Requires-Dist: dash-html-components ==2.0.0
Requires-Dist: dash-table ==5.0.0
Requires-Dist: et-xmlfile ==1.1.0
Requires-Dist: fonttools ==4.51.0
Requires-Dist: greenlet ==3.0.3
Requires-Dist: kiwisolver ==1.4.5
Requires-Dist: markupsafe ==2.1.5
Requires-Dist: matplotlib ==3.5.3
Requires-Dist: mordred ==1.2.0
Requires-Dist: networkx ==2.8.8
Requires-Dist: numpy ==1.26.4
Requires-Dist: openpyxl ==3.1.2
Requires-Dist: pandas ==2.2.2
Requires-Dist: pillow ==10.3.0
Requires-Dist: pycairo ==1.23.0
Requires-Dist: pysocks ==1.7.1
Requires-Dist: python-dateutil ==2.9.0.post0
Requires-Dist: pytz ==2024.1
Requires-Dist: pyyaml ==6.0.2rc1
Requires-Dist: reportlab ==3.6.13
Requires-Dist: scipy ==1.13.1
Requires-Dist: sqlalchemy ==2.0.30
Requires-Dist: tzdata ==2024.1
Requires-Dist: unicodedata2 ==15.1.0
Requires-Dist: PyYAML
Requires-Dist: pandas >=2.0.2
